<?xml version="1.0" encoding="UTF-8" standalone="yes" ?>
<Items>
<Item>
<ID>1</ID>
<EtpName>Сбербанк-АСТ -  электронная торговая площадка</EtpName>
<EtpLink>https://www.tenderguru.ru/api2.0/export?e1=1&amp;api_code=</EtpLink></Item>
<Item>
<ID>2</ID>
<EtpName>Росэлторг (roseltorg) - Единая электронная торговая площадка </EtpName>
<EtpLink>https://www.tenderguru.ru/api2.0/export?e2=1&amp;api_code=</EtpLink></Item>
<Item>
<ID>3</ID>
<EtpName>Система электронных торгов ЗаказРф (zakazrf)</EtpName>
<EtpLink>https://www.tenderguru.ru/api2.0/export?e3=1&amp;api_code=</EtpLink></Item>
<Item>
<ID>12</ID>
<EtpName>ЭТП «Фабрикант»</EtpName>
<EtpLink>https://www.tenderguru.ru/api2.0/export?e12=1&amp;api_code=</EtpLink></Item>
<Item>
<ID>14</ID>
<EtpName>SETonline</EtpName>
<EtpLink>https://www.tenderguru.ru/api2.0/export?e14=1&amp;api_code=</EtpLink></Item>
<Item>
<ID>16</ID>
<EtpName>РТС-тендер</EtpName>
<EtpLink>https://www.tenderguru.ru/api2.0/export?e16=1&amp;api_code=</EtpLink></Item>
<Item>
<ID>17</ID>
<EtpName>Национальная электронная площадка (бывшая ЭТП ММВБ), теперь ЭТП «Фабрикант»</EtpName>
<EtpLink>https://www.tenderguru.ru/api2.0/export?e17=1&amp;api_code=</EtpLink></Item>
<Item>
<ID>18</ID>
<EtpName>Аукционный Конкурсный Дом</EtpName>
<EtpLink>https://www.tenderguru.ru/api2.0/export?e18=1&amp;api_code=</EtpLink></Item>
<Item>
<ID>19</ID>
<EtpName>Электронная торговая площадка ONLINECONTRACT (Онлайнконтракт)</EtpName>
<EtpLink>https://www.tenderguru.ru/api2.0/export?e19=1&amp;api_code=</EtpLink></Item>
<Item>
<ID>20</ID>
<EtpName>Электронная торговая площадка «ИнвестЭнергосервис»</EtpName>
<EtpLink>https://www.tenderguru.ru/api2.0/export?e20=1&amp;api_code=</EtpLink></Item>
<Item>
<ID>21</ID>
<EtpName>Международный центр электронных торгов B2B-Center</EtpName>
<EtpLink>https://www.tenderguru.ru/api2.0/export?e21=1&amp;api_code=</EtpLink></Item>
<Item>
<ID>97</ID>
<EtpName>ЭТП "ТендерГуру"</EtpName>
<EtpLink>https://www.tenderguru.ru/api2.0/export?e97=1&amp;api_code=</EtpLink></Item>
<Item>
<ID>22</ID>
<EtpName>Торговая Система «Оборонторг»</EtpName>
<EtpLink>https://www.tenderguru.ru/api2.0/export?e22=1&amp;api_code=</EtpLink></Item>
<Item>
<ID>23</ID>
<EtpName>Электронная торговая площадка ОМК</EtpName>
<EtpLink>https://www.tenderguru.ru/api2.0/export?e23=1&amp;api_code=</EtpLink></Item>
<Item>
<ID>24</ID>
<EtpName>Tender.Pro (Тендер Про)</EtpName>
<EtpLink>https://www.tenderguru.ru/api2.0/export?e24=1&amp;api_code=</EtpLink></Item>
<Item>
<ID>25</ID>
<EtpName>ЗАО «Сибирская аграрная группа»</EtpName>
<EtpLink>https://www.tenderguru.ru/api2.0/export?e25=1&amp;api_code=</EtpLink></Item>
<Item>
<ID>26</ID>
<EtpName>Закупки для коммерческих заказчиков com.sberbank-ast.ru</EtpName>
<EtpLink>https://www.tenderguru.ru/api2.0/export?e26=1&amp;api_code=</EtpLink></Item>
<Item>
<ID>27</ID>
<EtpName>Закупки ОАО «Сбербанк России»</EtpName>
<EtpLink>https://www.tenderguru.ru/api2.0/export?e27=1&amp;api_code=</EtpLink></Item>
<Item>
<ID>28</ID>
<EtpName>Автоматизированная торговая площадка trade.sberbank-ast.ru</EtpName>
<EtpLink>https://www.tenderguru.ru/api2.0/export?e28=1&amp;api_code=</EtpLink></Item>
<Item>
<ID>29</ID>
<EtpName>ОАО "Московская теплосетевая компания" - Электронная торговая площадка</EtpName>
<EtpLink>https://www.tenderguru.ru/api2.0/export?e29=1&amp;api_code=</EtpLink></Item>
<Item>
<ID>30</ID>
<EtpName>ТЗС Электра</EtpName>
<EtpLink>https://www.tenderguru.ru/api2.0/export?e30=1&amp;api_code=</EtpLink></Item>
<Item>
<ID>31</ID>
<EtpName>Система коммерческих торгов com.roseltorg.ru</EtpName>
<EtpLink>https://www.tenderguru.ru/api2.0/export?e31=1&amp;api_code=</EtpLink></Item>
<Item>
<ID>32</ID>
<EtpName>Торги заказчиков атомной отрасли atom.roseltorg.ru</EtpName>
<EtpLink>https://www.tenderguru.ru/api2.0/export?e32=1&amp;api_code=</EtpLink></Item>
<Item>
<ID>33</ID>
<EtpName>Экономический портал Белгородской области</EtpName>
<EtpLink>https://www.tenderguru.ru/api2.0/export?e33=1&amp;api_code=</EtpLink></Item>
<Item>
<ID>34</ID>
<EtpName>Площадка ETPRF (ЭТП РФ)</EtpName>
<EtpLink>https://www.tenderguru.ru/api2.0/export?e34=1&amp;api_code=</EtpLink></Item>
<Item>
<ID>35</ID>
<EtpName>ЭТП ОАО "Белон"</EtpName>
<EtpLink>https://www.tenderguru.ru/api2.0/export?e35=1&amp;api_code=</EtpLink></Item>
<Item>
<ID>36</ID>
<EtpName>Группа электронных площадок ОТС-тендер</EtpName>
<EtpLink>https://www.tenderguru.ru/api2.0/export?e36=1&amp;api_code=</EtpLink></Item>
<Item>
<ID>37</ID>
<EtpName>ЭТП Российский аукционный дом (РАД)</EtpName>
<EtpLink>https://www.tenderguru.ru/api2.0/export?e37=1&amp;api_code=</EtpLink></Item>
<Item>
<ID>38</ID>
<EtpName>Торговая Система "Спецстройторг"</EtpName>
<EtpLink>https://www.tenderguru.ru/api2.0/export?e38=1&amp;api_code=</EtpLink></Item>
<Item>
<ID>39</ID>
<EtpName>Торговая система "ГазНефтеторг.ру"</EtpName>
<EtpLink>https://www.tenderguru.ru/api2.0/export?e39=1&amp;api_code=</EtpLink></Item>
<Item>
<ID>40</ID>
<EtpName>ЭТП Дальневосточного Федерального Округа</EtpName>
<EtpLink>https://www.tenderguru.ru/api2.0/export?e40=1&amp;api_code=</EtpLink></Item>
<Item>
<ID>41</ID>
<EtpName>ЭТП Южного Федерального Округа</EtpName>
<EtpLink>https://www.tenderguru.ru/api2.0/export?e41=1&amp;api_code=</EtpLink></Item>
<Item>
<ID>42</ID>
<EtpName>ЭТП Приволжского Федерального Округа</EtpName>
<EtpLink>https://www.tenderguru.ru/api2.0/export?e42=1&amp;api_code=</EtpLink></Item>
<Item>
<ID>43</ID>
<EtpName>ЭТП Сибирского Федерального Округа</EtpName>
<EtpLink>https://www.tenderguru.ru/api2.0/export?e43=1&amp;api_code=</EtpLink></Item>
<Item>
<ID>44</ID>
<EtpName>ЭТП Уральского Федерального Округа</EtpName>
<EtpLink>https://www.tenderguru.ru/api2.0/export?e44=1&amp;api_code=</EtpLink></Item>
<Item>
<ID>45</ID>
<EtpName>Закупки ОАО "Ростелеком" на roseltorg.ru</EtpName>
<EtpLink>https://www.tenderguru.ru/api2.0/export?e45=1&amp;api_code=</EtpLink></Item>
<Item>
<ID>46</ID>
<EtpName>Электронная торговая площадка ЭТП ГПБ</EtpName>
<EtpLink>https://www.tenderguru.ru/api2.0/export?e46=1&amp;api_code=</EtpLink></Item>
<Item>
<ID>47</ID>
<EtpName>Торги Сбербанк-АСТ по 223-ФЗ</EtpName>
<EtpLink>https://www.tenderguru.ru/api2.0/export?e47=1&amp;api_code=</EtpLink></Item>
<Item>
<ID>48</ID>
<EtpName>ЭТП ООО «Коммерсантъ  КАРТОТЕКА»</EtpName>
<EtpLink>https://www.tenderguru.ru/api2.0/export?e48=1&amp;api_code=</EtpLink></Item>
<Item>
<ID>49</ID>
<EtpName>ЭТП Северсталь</EtpName>
<EtpLink>https://www.tenderguru.ru/api2.0/export?e49=1&amp;api_code=</EtpLink></Item>
<Item>
<ID>50</ID>
<EtpName>Электронная торговая площадка Тендер</EtpName>
<EtpLink>https://www.tenderguru.ru/api2.0/export?e50=1&amp;api_code=</EtpLink></Item>
<Item>
<ID>53</ID>
<EtpName>ЭТП Закупки.ру</EtpName>
<EtpLink>https://www.tenderguru.ru/api2.0/export?e53=1&amp;api_code=</EtpLink></Item>
<Item>
<ID>54</ID>
<EtpName>Торгово-закупочная площадка ОАО "Татнефть"</EtpName>
<EtpLink>https://www.tenderguru.ru/api2.0/export?e54=1&amp;api_code=</EtpLink></Item>
<Item>
<ID>55</ID>
<EtpName>ЭТП «Электронный капитал» </EtpName>
<EtpLink>https://www.tenderguru.ru/api2.0/export?e55=1&amp;api_code=</EtpLink></Item>
<Item>
<ID>56</ID>
<EtpName>ОЭТП</EtpName>
<EtpLink>https://www.tenderguru.ru/api2.0/export?e56=1&amp;api_code=</EtpLink></Item>
<Item>
<ID>58</ID>
<EtpName>Единая система торговых процедур</EtpName>
<EtpLink>https://www.tenderguru.ru/api2.0/export?e58=1&amp;api_code=</EtpLink></Item>
<Item>
<ID>59</ID>
<EtpName>Система электронных торгов. Коммерческие закупки</EtpName>
<EtpLink>https://www.tenderguru.ru/api2.0/export?e59=1&amp;api_code=</EtpLink></Item>
<Item>
<ID>60</ID>
<EtpName>Торговая Система «ТЭК-Торг»</EtpName>
<EtpLink>https://www.tenderguru.ru/api2.0/export?e60=1&amp;api_code=</EtpLink></Item>
<Item>
<ID>63</ID>
<EtpName>ЭТП  «Закупочные и маркетинговые системы»</EtpName>
<EtpLink>https://www.tenderguru.ru/api2.0/export?e63=1&amp;api_code=</EtpLink></Item>
<Item>
<ID>65</ID>
<EtpName>ООО "Электронная торговая площадка БЭСТ"</EtpName>
<EtpLink>https://www.tenderguru.ru/api2.0/export?e65=1&amp;api_code=</EtpLink></Item>
<Item>
<ID>66</ID>
<EtpName>ЭТП ООО "Закупочные и маркетинговые системы "RB2B.RU"</EtpName>
<EtpLink>https://www.tenderguru.ru/api2.0/export?e66=1&amp;api_code=</EtpLink></Item>
<Item>
<ID>67</ID>
<EtpName>Торговая Система "Пикон.ру" </EtpName>
<EtpLink>https://www.tenderguru.ru/api2.0/export?e67=1&amp;api_code=</EtpLink></Item>
<Item>
<ID>70</ID>
<EtpName>Электронная торговая площадка ЛотЭксперт</EtpName>
<EtpLink>https://www.tenderguru.ru/api2.0/export?e70=1&amp;api_code=</EtpLink></Item>
<Item>
<ID>68</ID>
<EtpName>Электронная площадка ЗАО "Биржа "Санкт-Петербург"</EtpName>
<EtpLink>https://www.tenderguru.ru/api2.0/export?e68=1&amp;api_code=</EtpLink></Item>
<Item>
<ID>71</ID>
<EtpName>Электронная Торговая Площадка 223</EtpName>
<EtpLink>https://www.tenderguru.ru/api2.0/export?e71=1&amp;api_code=</EtpLink></Item>
<Item>
<ID>69</ID>
<EtpName>Торговая система RHtorg</EtpName>
<EtpLink>https://www.tenderguru.ru/api2.0/export?e69=1&amp;api_code=</EtpLink></Item>
<Item>
<ID>72</ID>
<EtpName>Электронная площадка "24тендер"</EtpName>
<EtpLink>https://www.tenderguru.ru/api2.0/export?e72=1&amp;api_code=</EtpLink></Item>
<Item>
<ID>75</ID>
<EtpName>ЭТП «ОСТ»</EtpName>
<EtpLink>https://www.tenderguru.ru/api2.0/export?e75=1&amp;api_code=</EtpLink></Item>
<Item>
<ID>74</ID>
<EtpName>E-tender М.Видео</EtpName>
<EtpLink>https://www.tenderguru.ru/api2.0/export?e74=1&amp;api_code=</EtpLink></Item>
<Item>
<ID>77</ID>
<EtpName>Электронная площадка ЗАО "Биржа "Санкт-Петербург"</EtpName>
<EtpLink>https://www.tenderguru.ru/api2.0/export?e77=1&amp;api_code=</EtpLink></Item>
<Item>
<ID>76</ID>
<EtpName>«РТС-тендер» коммерческая закупка</EtpName>
<EtpLink>https://www.tenderguru.ru/api2.0/export?e76=1&amp;api_code=</EtpLink></Item>
<Item>
<ID>78</ID>
<EtpName>ЭТП «ТЭК-Торг» секция ООО «Газпром бурение»</EtpName>
<EtpLink>https://www.tenderguru.ru/api2.0/export?e78=1&amp;api_code=</EtpLink></Item>
<Item>
<ID>80</ID>
<EtpName>Электронная площадка RFP</EtpName>
<EtpLink>https://www.tenderguru.ru/api2.0/export?e80=1&amp;api_code=</EtpLink></Item>
<Item>
<ID>81</ID>
<EtpName>ЭТП «Федерация»</EtpName>
<EtpLink>https://www.tenderguru.ru/api2.0/export?e81=1&amp;api_code=</EtpLink></Item>
<Item>
<ID>82</ID>
<EtpName>ЭТП "Дом Закупок"</EtpName>
<EtpLink>https://www.tenderguru.ru/api2.0/export?e82=1&amp;api_code=</EtpLink></Item>
<Item>
<ID>83</ID>
<EtpName>ЭЛЕКТРОННЫЙ МАГАЗИН РТС-МАРКЕТ (Закупки малого объема)</EtpName>
<EtpLink>https://www.tenderguru.ru/api2.0/export?e83=1&amp;api_code=</EtpLink></Item>
<Item>
<ID>84</ID>
<EtpName>Электронный магазин Московской области (Закупки малого объема)</EtpName>
<EtpLink>https://www.tenderguru.ru/api2.0/export?e84=1&amp;api_code=</EtpLink></Item>
<Item>
<ID>85</ID>
<EtpName>Электронная торговая площадка etpzakaz</EtpName>
<EtpLink>https://www.tenderguru.ru/api2.0/export?e85=1&amp;api_code=</EtpLink></Item>
<Item>
<ID>79</ID>
<EtpName>Портал поставщиков</EtpName>
<EtpLink>https://www.tenderguru.ru/api2.0/export?e79=1&amp;api_code=</EtpLink></Item>
<Item>
<ID>64</ID>
<EtpName>Закупки ОАО АФК "Система" </EtpName>
<EtpLink>https://www.tenderguru.ru/api2.0/export?e64=1&amp;api_code=</EtpLink></Item>
<Item>
<ID>90</ID>
<EtpName>Электронная площадка Томской области</EtpName>
<EtpLink>https://www.tenderguru.ru/api2.0/export?e90=1&amp;api_code=</EtpLink></Item>
<Item>
<ID>86</ID>
<EtpName>Малые закупки Удмуртской Республики</EtpName>
<EtpLink>https://www.tenderguru.ru/api2.0/export?e86=1&amp;api_code=</EtpLink></Item>
<Item>
<ID>92</ID>
<EtpName>Автоматизированная система торгов государственного оборонного заказа (АСТ ГОЗ)</EtpName>
<EtpLink>https://www.tenderguru.ru/api2.0/export?e92=1&amp;api_code=</EtpLink></Item>
<Item>
<ID>87</ID>
<EtpName>Портал малых закупок Воронежской области</EtpName>
<EtpLink>https://www.tenderguru.ru/api2.0/export?e87=1&amp;api_code=</EtpLink></Item>
<Item>
<ID>88</ID>
<EtpName>Малые закупки Смоленской области</EtpName>
<EtpLink>https://www.tenderguru.ru/api2.0/export?e88=1&amp;api_code=</EtpLink></Item>
<Item>
<ID>89</ID>
<EtpName>Закупки малого объема Мурманской области</EtpName>
<EtpLink>https://www.tenderguru.ru/api2.0/export?e89=1&amp;api_code=</EtpLink></Item>
<Item>
<ID>94</ID>
<EtpName>Единый агрегатор торговли «Березка» </EtpName>
<EtpLink>https://www.tenderguru.ru/api2.0/export?e94=1&amp;api_code=</EtpLink></Item>
<Item>
<ID>101</ID>
<EtpName>ЭТП Нефть Регион</EtpName>
<EtpLink>https://www.tenderguru.ru/api2.0/export?e101=1&amp;api_code=</EtpLink></Item>
<Item>
<ID>105</ID>
<EtpName>Агентство по государственному заказу Республики Татарстан. Биржевая площадка</EtpName>
<EtpLink>https://www.tenderguru.ru/api2.0/export?e105=1&amp;api_code=</EtpLink></Item>
<Item>
<ID>102</ID>
<EtpName>ЭТП Бидзаар</EtpName>
<EtpLink>https://www.tenderguru.ru/api2.0/export?e102=1&amp;api_code=</EtpLink></Item>
<Item>
<ID>104</ID>
<EtpName>Малые закупки р.Мордовия</EtpName>
<EtpLink>https://www.tenderguru.ru/api2.0/export?e104=1&amp;api_code=</EtpLink></Item>
<Item>
<ID>93</ID>
<EtpName>Малые закупки Самарской области</EtpName>
<EtpLink>https://www.tenderguru.ru/api2.0/export?e93=1&amp;api_code=</EtpLink></Item>
<Item>
<ID>103</ID>
<EtpName>Малые закупки  Калужской области</EtpName>
<EtpLink>https://www.tenderguru.ru/api2.0/export?e103=1&amp;api_code=</EtpLink></Item>
<Item>
<ID>106</ID>
<EtpName>ЭТП «Комита»</EtpName>
<EtpLink>https://www.tenderguru.ru/api2.0/export?e106=1&amp;api_code=</EtpLink></Item>
<Item>
<ID>107</ID>
<EtpName>Электронная торговая площадка – ПАО «ГЕОТЕК Сейсморазведка».</EtpName>
<EtpLink>https://www.tenderguru.ru/api2.0/export?e107=1&amp;api_code=</EtpLink></Item>
<Item>
<ID>108</ID>
<EtpName>ЭЛЕКТРОННАЯ ТОРГОВАЯ ПЛОЩАДКА ГК "СПЕКТРУМ"</EtpName>
<EtpLink>https://www.tenderguru.ru/api2.0/export?e108=1&amp;api_code=</EtpLink></Item>
<Item>
<ID>109</ID>
<EtpName>малые закупки Ярославской облости</EtpName>
<EtpLink>https://www.tenderguru.ru/api2.0/export?e109=1&amp;api_code=</EtpLink></Item>
<Item>
<ID>110</ID>
<EtpName>АвтоТрансИнфо</EtpName>
<EtpLink>https://www.tenderguru.ru/api2.0/export?e110=1&amp;api_code=</EtpLink></Item>
<Item>
<ID>111</ID>
<EtpName>RusCable.Ru</EtpName>
<EtpLink>https://www.tenderguru.ru/api2.0/export?e111=1&amp;api_code=</EtpLink></Item>
<Item>
<ID>114</ID>
<EtpName>ЭТП" Интеллект центр"</EtpName>
<EtpLink>https://www.tenderguru.ru/api2.0/export?e114=1&amp;api_code=</EtpLink></Item>
<Item>
<ID>115</ID>
<EtpName>ЭТП "Автодор"</EtpName>
<EtpLink>https://www.tenderguru.ru/api2.0/export?e115=1&amp;api_code=</EtpLink></Item>
<Item>
<ID>116</ID>
<EtpName>"Электронный магазин закупок малого объема Петрозаводского городского округа"</EtpName>
<EtpLink>https://www.tenderguru.ru/api2.0/export?e116=1&amp;api_code=</EtpLink></Item>
<Item>
<ID>118</ID>
<EtpName>Портал закупок "Дом.ru."</EtpName>
<EtpLink>https://www.tenderguru.ru/api2.0/export?e118=1&amp;api_code=</EtpLink></Item>
<Item>
<ID>119</ID>
<EtpName>ЭТП  STI-Trade (АО «Смарт Технологии Инвест» (АО «СТИ»))</EtpName>
<EtpLink>https://www.tenderguru.ru/api2.0/export?e119=1&amp;api_code=</EtpLink></Item>
<Item>
<ID>120</ID>
<EtpName>SberB2B (СберБ2б)</EtpName>
<EtpLink>https://www.tenderguru.ru/api2.0/export?e120=1&amp;api_code=</EtpLink></Item>
<Item>
<ID>121</ID>
<EtpName>Электронная торговая площадка ООО "Трансстроймеханизация"</EtpName>
<EtpLink>https://www.tenderguru.ru/api2.0/export?e121=1&amp;api_code=</EtpLink></Item>
<Item>
<ID>123</ID>
<EtpName>ЭТП АО «Форум-групп»</EtpName>
<EtpLink>https://www.tenderguru.ru/api2.0/export?e123=1&amp;api_code=</EtpLink></Item>
<Item>
<ID>124</ID>
<EtpName>Электронная торговая площадка ПАО "Орелстрой"</EtpName>
<EtpLink>https://www.tenderguru.ru/api2.0/export?e124=1&amp;api_code=</EtpLink></Item>
<Item>
<ID>125</ID>
<EtpName>СТРАТЕГ-электронная торговая площадка</EtpName>
<EtpLink>https://www.tenderguru.ru/api2.0/export?e125=1&amp;api_code=</EtpLink></Item>
<Item>
<ID>126</ID>
<EtpName>Электронная торговая площадка Нефть-B2B</EtpName>
<EtpLink>https://www.tenderguru.ru/api2.0/export?e126=1&amp;api_code=</EtpLink></Item>
<Item>
<ID>127</ID>
<EtpName>Система электронных торгов VLADZAKUPKI.RU.</EtpName>
<EtpLink>https://www.tenderguru.ru/api2.0/export?e127=1&amp;api_code=</EtpLink></Item>
<Item>
<ID>95</ID>
<EtpName>Малые закупки Тверской облости</EtpName>
<EtpLink>https://www.tenderguru.ru/api2.0/export?e95=1&amp;api_code=</EtpLink></Item>
<Item>
<ID>96</ID>
<EtpName>Торговая площадка bidbe</EtpName>
<EtpLink>https://www.tenderguru.ru/api2.0/export?e96=1&amp;api_code=</EtpLink></Item>
</Items>